wre_commit/__init__.py
wre_commit/__main__.py
wre_commit/main.py
wre_commit-1.0.7.dist-info/LICENSE
wre_commit-1.0.7.dist-info/METADATA
wre_commit-1.0.7.dist-info/WHEEL
wre_commit-1.0.7.dist-info/entry_points.txt
wre_commit-1.0.7.dist-info/top_level.txt
wre_commit-1.0.7.dist-info/RECORD
