Metadata-Version: 2.1
Name: wre-commit
Version: 1.0.7
Summary: A wrapper for pre-commit.
Home-page: https://github.com/JakeFromTheDark/wre-commit
Author: Kamil Jakubovic
Author-email: kamil.jakubovic@gmail.com
License: GNU GPL v3
Platform: UNKNOWN
Classifier: License :: OSI Approved :: GNU General Public License v3 (GPLv3)
Classifier: Operating System :: OS Independent
Classifier: Programming Language :: Python :: 3
Classifier: Programming Language :: Python :: 3 :: Only
Classifier: Programming Language :: Python :: Implementation :: CPython
Classifier: Programming Language :: Python :: Implementation :: PyPy
Requires-Python: >=3.0
